{
    "request": {
      "PromoAdsStatus": true,
      "PromoAds": [
       
        {
          "index": "1",
          "title": "OTT Promo",
          "BlurbPoster": "https://frsied21.github.io/launcher/popUp_Dv1_small.png",
          "PopUpPoster": "https://frsied21.github.io/launcher/Final.popUp_3posters-temp.jpg",
          "extRedirection": "https://selfcare.unifi.com.my/service/tvapps/my-entertainment",
          "promoStatus": true
        },
        {
          "index": "2",
          "title": "Unifi Promo",
          "BlurbPoster": "https://frsied21.github.io/launcher/popUp_Dv1_small.png",
          "PopUpPoster": "https://frsied21.github.io/launcher/Final.vod_Upick2_1280x1885.jpg",
          "extRedirection": "https://selfcare.unifi.com.my/service/tvapps/my-entertainment",
          "promoStatus": false
        },
        {
          "index": "3",
          "title": "Promo",
          "BlurbPoster": "https://frsied21.github.io/launcher/popUp_Dv1_small.png",
          "PopUpPoster": "https://frsied21.github.io/launcher/Final.popUp_MAX-UC.jpg",
          "extRedirection": "https://selfcare.unifi.com.my/service/tvapps/my-entertainment",
          "promoStatus": false
        }
      ]
    }
  }
  
